[
  {
    "item_id": 0,
    "price_id": 1,
    "amount": 150,
    "id": 1,
    "item_type": 5
  },
  {
    "item_id": 0,
    "price_id": 2,
    "amount": 750,
    "id": 2,
    "item_type": 5
  },
  {
    "item_id": 0,
    "price_id": 3,
    "amount": 30,
    "id": 3,
    "item_type": 5
  },
  {
    "item_id": 0,
    "price_id": 4,
    "amount": 2250,
    "id": 4,
    "item_type": 5
  },
  {
    "item_id": 0,
    "price_id": 5,
    "amount": 300,
    "id": 5,
    "item_type": 5
  },
  {
    "item_id": 0,
    "price_id": 10,
    "amount": 50,
    "id": 6,
    "item_type": 5
  },
  {
    "item_id": 0,
    "price_id": 11,
    "amount": 25,
    "id": 7,
    "item_type": 5
  },
  {
    "item_id": 0,
    "price_id": 12,
    "amount": 5,
    "id": 8,
    "item_type": 5
  },
  {
    "item_id": 0,
    "price_id": 13,
    "amount": 10000,
    "id": 9,
    "item_type": 4
  },
  {
    "item_id": 0,
    "price_id": 21,
    "amount": 100,
    "id": 10,
    "item_type": 5
  },
  {
    "item_id": 0,
    "price_id": 22,
    "amount": 200,
    "id": 11,
    "item_type": 5
  },
  {
    "item_id": 0,
    "price_id": 23,
    "amount": 700,
    "id": 12,
    "item_type": 5
  },
  {
    "item_id": 0,
    "price_id": 24,
    "amount": 1000,
    "id": 13,
    "item_type": 5
  },
  {
    "item_id": 0,
    "price_id": 25,
    "amount": 1450,
    "id": 14,
    "item_type": 5
  },
  {
    "item_id": 0,
    "price_id": 26,
    "amount": 90,
    "id": 15,
    "item_type": 5
  },
  {
    "item_id": 0,
    "price_id": 27,
    "amount": 155,
    "id": 16,
    "item_type": 5
  },
  {
    "item_id": 0,
    "price_id": 28,
    "amount": 210,
    "id": 17,
    "item_type": 5
  },
  {
    "item_id": 0,
    "price_id": 29,
    "amount": 315,
    "id": 18,
    "item_type": 5
  },
  {
    "item_id": 0,
    "price_id": 30,
    "amount": 420,
    "id": 19,
    "item_type": 5
  },
  {
    "item_id": 0,
    "price_id": 31,
    "amount": 650,
    "id": 20,
    "item_type": 5
  },
  {
    "item_id": 0,
    "price_id": 32,
    "amount": 900,
    "id": 21,
    "item_type": 5
  },
  {
    "item_id": 0,
    "price_id": 33,
    "amount": 725,
    "id": 22,
    "item_type": 5
  },
  {
    "item_id": 0,
    "price_id": 50,
    "amount": 50,
    "id": 23,
    "item_type": 5
  },
  {
    "item_id": 0,
    "price_id": 75,
    "amount": 75,
    "id": 24,
    "item_type": 5
  },
  {
    "item_id": 0,
    "price_id": 99,
    "amount": 100,
    "id": 25,
    "item_type": 5
  },
  {
    "item_id": 0,
    "price_id": 100,
    "amount": 25,
    "id": 26,
    "item_type": 5
  },
  {
    "item_id": 0,
    "price_id": 101,
    "amount": 50000,
    "id": 27,
    "item_type": 4
  },
  {
    "item_id": 0,
    "price_id": 102,
    "amount": 10,
    "id": 28,
    "item_type": 5
  },
  {
    "item_id": 0,
    "price_id": 103,
    "amount": 1,
    "id": 29,
    "item_type": 2
  },
  {
    "item_id": 0,
    "price_id": 104,
    "amount": 100000,
    "id": 30,
    "item_type": 4
  },
  {
    "item_id": 0,
    "price_id": 105,
    "amount": 0,
    "id": 31,
    "item_type": 5
  },
  {
    "item_id": 0,
    "price_id": 149,
    "amount": 100,
    "id": 32,
    "item_type": 5
  },
  {
    "item_id": 0,
    "price_id": 150,
    "amount": 150,
    "id": 33,
    "item_type": 5
  },
  {
    "item_id": 0,
    "price_id": 200,
    "amount": 20,
    "id": 34,
    "item_type": 5
  },
  {
    "item_id": 0,
    "price_id": 250,
    "amount": 250,
    "id": 35,
    "item_type": 5
  },
  {
    "item_id": 0,
    "price_id": 300,
    "amount": 300,
    "id": 36,
    "item_type": 5
  },
  {
    "item_id": 0,
    "price_id": 400,
    "amount": 1,
    "id": 37,
    "item_type": 2
  },
  {
    "item_id": 0,
    "price_id": 401,
    "amount": 2,
    "id": 38,
    "item_type": 2
  },
  {
    "item_id": 0,
    "price_id": 402,
    "amount": 4,
    "id": 39,
    "item_type": 2
  },
  {
    "item_id": 0,
    "price_id": 403,
    "amount": 9,
    "id": 40,
    "item_type": 2
  },
  {
    "item_id": 0,
    "price_id": 404,
    "amount": 14,
    "id": 41,
    "item_type": 2
  },
  {
    "item_id": 0,
    "price_id": 500,
    "amount": 500,
    "id": 42,
    "item_type": 5
  },
  {
    "item_id": 0,
    "price_id": 750,
    "amount": 750,
    "id": 43,
    "item_type": 5
  },
  {
    "item_id": 0,
    "price_id": 998,
    "amount": 3,
    "id": 44,
    "item_type": 2
  },
  {
    "item_id": 0,
    "price_id": 999,
    "amount": 5,
    "id": 45,
    "item_type": 2
  },
  {
    "item_id": 0,
    "price_id": 1000,
    "amount": 100,
    "id": 46,
    "item_type": 5
  },
  {
    "item_id": 0,
    "price_id": 1001,
    "amount": 50,
    "id": 47,
    "item_type": 5
  },
  {
    "item_id": 0,
    "price_id": 1002,
    "amount": 150,
    "id": 48,
    "item_type": 5
  },
  {
    "item_id": 0,
    "price_id": 1003,
    "amount": 450,
    "id": 49,
    "item_type": 5
  },
  {
    "item_id": 0,
    "price_id": 1004,
    "amount": 800,
    "id": 50,
    "item_type": 5
  },
  {
    "item_id": 0,
    "price_id": 1005,
    "amount": 1400,
    "id": 51,
    "item_type": 5
  },
  {
    "item_id": 0,
    "price_id": 1006,
    "amount": 1950,
    "id": 52,
    "item_type": 5
  },
  {
    "item_id": 0,
    "price_id": 1007,
    "amount": 2800,
    "id": 53,
    "item_type": 5
  },
  {
    "item_id": 0,
    "price_id": 1101,
    "amount": 50,
    "id": 54,
    "item_type": 5
  },
  {
    "item_id": 0,
    "price_id": 1102,
    "amount": 150,
    "id": 55,
    "item_type": 5
  },
  {
    "item_id": 0,
    "price_id": 1103,
    "amount": 250,
    "id": 56,
    "item_type": 5
  },
  {
    "item_id": 0,
    "price_id": 1104,
    "amount": 360,
    "id": 57,
    "item_type": 5
  },
  {
    "item_id": 0,
    "price_id": 1105,
    "amount": 520,
    "id": 58,
    "item_type": 5
  },
  {
    "item_id": 0,
    "price_id": 1106,
    "amount": 700,
    "id": 59,
    "item_type": 5
  },
  {
    "item_id": 0,
    "price_id": 1107,
    "amount": 900,
    "id": 60,
    "item_type": 5
  },
  {
    "item_id": 0,
    "price_id": 1201,
    "amount": 25,
    "id": 61,
    "item_type": 5
  },
  {
    "item_id": 0,
    "price_id": 1202,
    "amount": 400,
    "id": 62,
    "item_type": 5
  },
  {
    "item_id": 0,
    "price_id": 1203,
    "amount": 550,
    "id": 63,
    "item_type": 5
  },
  {
    "item_id": 0,
    "price_id": 1204,
    "amount": 950,
    "id": 64,
    "item_type": 5
  },
  {
    "item_id": 0,
    "price_id": 1250,
    "amount": 1250,
    "id": 65,
    "item_type": 5
  },
  {
    "item_id": 0,
    "price_id": 1500,
    "amount": 1500,
    "id": 66,
    "item_type": 5
  },
  {
    "item_id": 0,
    "price_id": 1750,
    "amount": 1750,
    "id": 67,
    "item_type": 5
  },
  {
    "item_id": 0,
    "price_id": 2000,
    "amount": 0,
    "id": 68,
    "item_type": 4
  },
  {
    "item_id": 0,
    "price_id": 2001,
    "amount": 300,
    "id": 69,
    "item_type": 4
  },
  {
    "item_id": 0,
    "price_id": 2002,
    "amount": 350,
    "id": 70,
    "item_type": 4
  },
  {
    "item_id": 0,
    "price_id": 2003,
    "amount": 400,
    "id": 71,
    "item_type": 4
  },
  {
    "item_id": 0,
    "price_id": 2004,
    "amount": 450,
    "id": 72,
    "item_type": 4
  },
  {
    "item_id": 0,
    "price_id": 2005,
    "amount": 500,
    "id": 73,
    "item_type": 4
  },
  {
    "item_id": 0,
    "price_id": 2006,
    "amount": 1000,
    "id": 74,
    "item_type": 4
  },
  {
    "item_id": 0,
    "price_id": 2007,
    "amount": 1250,
    "id": 75,
    "item_type": 4
  },
  {
    "item_id": 0,
    "price_id": 2008,
    "amount": 1500,
    "id": 76,
    "item_type": 4
  },
  {
    "item_id": 0,
    "price_id": 2009,
    "amount": 1750,
    "id": 77,
    "item_type": 4
  },
  {
    "item_id": 0,
    "price_id": 2010,
    "amount": 2000,
    "id": 78,
    "item_type": 4
  },
  {
    "item_id": 0,
    "price_id": 2011,
    "amount": 2400,
    "id": 79,
    "item_type": 4
  },
  {
    "item_id": 0,
    "price_id": 2012,
    "amount": 2800,
    "id": 80,
    "item_type": 4
  },
  {
    "item_id": 0,
    "price_id": 2013,
    "amount": 3200,
    "id": 81,
    "item_type": 4
  },
  {
    "item_id": 0,
    "price_id": 2014,
    "amount": 3600,
    "id": 82,
    "item_type": 4
  },
  {
    "item_id": 0,
    "price_id": 2015,
    "amount": 4000,
    "id": 83,
    "item_type": 4
  },
  {
    "item_id": 0,
    "price_id": 2016,
    "amount": 4500,
    "id": 84,
    "item_type": 4
  },
  {
    "item_id": 0,
    "price_id": 2017,
    "amount": 5000,
    "id": 85,
    "item_type": 4
  },
  {
    "item_id": 0,
    "price_id": 2018,
    "amount": 5500,
    "id": 86,
    "item_type": 4
  },
  {
    "item_id": 0,
    "price_id": 2019,
    "amount": 6000,
    "id": 87,
    "item_type": 4
  },
  {
    "item_id": 0,
    "price_id": 2020,
    "amount": 6500,
    "id": 88,
    "item_type": 4
  },
  {
    "item_id": 0,
    "price_id": 2021,
    "amount": 7000,
    "id": 89,
    "item_type": 4
  },
  {
    "item_id": 0,
    "price_id": 2022,
    "amount": 8000,
    "id": 90,
    "item_type": 4
  },
  {
    "item_id": 0,
    "price_id": 2023,
    "amount": 9000,
    "id": 91,
    "item_type": 4
  },
  {
    "item_id": 0,
    "price_id": 2024,
    "amount": 10000,
    "id": 92,
    "item_type": 4
  },
  {
    "item_id": 0,
    "price_id": 2025,
    "amount": 12500,
    "id": 93,
    "item_type": 4
  },
  {
    "item_id": 0,
    "price_id": 2026,
    "amount": 15000,
    "id": 94,
    "item_type": 4
  },
  {
    "item_id": 0,
    "price_id": 2027,
    "amount": 16500,
    "id": 95,
    "item_type": 4
  },
  {
    "item_id": 0,
    "price_id": 2028,
    "amount": 18000,
    "id": 96,
    "item_type": 4
  },
  {
    "item_id": 0,
    "price_id": 2029,
    "amount": 19500,
    "id": 97,
    "item_type": 4
  },
  {
    "item_id": 0,
    "price_id": 2030,
    "amount": 21000,
    "id": 98,
    "item_type": 4
  },
  {
    "item_id": 0,
    "price_id": 2031,
    "amount": 22500,
    "id": 99,
    "item_type": 4
  },
  {
    "item_id": 0,
    "price_id": 2032,
    "amount": 24000,
    "id": 100,
    "item_type": 4
  },
  {
    "item_id": 0,
    "price_id": 2033,
    "amount": 27000,
    "id": 101,
    "item_type": 4
  },
  {
    "item_id": 0,
    "price_id": 2034,
    "amount": 30000,
    "id": 102,
    "item_type": 4
  },
  {
    "item_id": 0,
    "price_id": 2035,
    "amount": 37500,
    "id": 103,
    "item_type": 4
  },
  {
    "item_id": 0,
    "price_id": 2036,
    "amount": 45000,
    "id": 104,
    "item_type": 4
  },
  {
    "item_id": 0,
    "price_id": 2037,
    "amount": 52500,
    "id": 105,
    "item_type": 4
  },
  {
    "item_id": 0,
    "price_id": 2038,
    "amount": 60000,
    "id": 106,
    "item_type": 4
  },
  {
    "item_id": 0,
    "price_id": 2039,
    "amount": 67500,
    "id": 107,
    "item_type": 4
  },
  {
    "item_id": 0,
    "price_id": 2040,
    "amount": 75000,
    "id": 108,
    "item_type": 4
  },
  {
    "item_id": 0,
    "price_id": 2041,
    "amount": 82500,
    "id": 109,
    "item_type": 4
  },
  {
    "item_id": 0,
    "price_id": 2042,
    "amount": 90000,
    "id": 110,
    "item_type": 4
  },
  {
    "item_id": 0,
    "price_id": 2043,
    "amount": 97500,
    "id": 111,
    "item_type": 4
  },
  {
    "item_id": 0,
    "price_id": 2044,
    "amount": 105000,
    "id": 112,
    "item_type": 4
  },
  {
    "item_id": 0,
    "price_id": 2045,
    "amount": 150000,
    "id": 113,
    "item_type": 4
  },
  {
    "item_id": 99,
    "price_id": 2099,
    "amount": 10,
    "id": 114,
    "item_type": 6
  },
  {
    "item_id": 0,
    "price_id": 2750,
    "amount": 2750,
    "id": 115,
    "item_type": 5
  },
  {
    "item_id": 0,
    "price_id": 3000,
    "amount": 1,
    "id": 116,
    "item_type": 2
  },
  {
    "item_id": 0,
    "price_id": 3001,
    "amount": 6,
    "id": 117,
    "item_type": 5
  },
  {
    "item_id": 0,
    "price_id": 4001,
    "amount": 25,
    "id": 118,
    "item_type": 5
  },
  {
    "item_id": 0,
    "price_id": 4002,
    "amount": 100,
    "id": 119,
    "item_type": 5
  },
  {
    "item_id": 0,
    "price_id": 4003,
    "amount": 300,
    "id": 120,
    "item_type": 5
  },
  {
    "item_id": 0,
    "price_id": 4004,
    "amount": 600,
    "id": 121,
    "item_type": 5
  },
  {
    "item_id": 0,
    "price_id": 4005,
    "amount": 1200,
    "id": 122,
    "item_type": 5
  },
  {
    "item_id": 0,
    "price_id": 4006,
    "amount": 1950,
    "id": 123,
    "item_type": 5
  },
  {
    "item_id": 0,
    "price_id": 4007,
    "amount": 2150,
    "id": 124,
    "item_type": 5
  },
  {
    "item_id": 0,
    "price_id": 4008,
    "amount": 50,
    "id": 125,
    "item_type": 5
  },
  {
    "item_id": 0,
    "price_id": 4009,
    "amount": 150,
    "id": 126,
    "item_type": 5
  },
  {
    "item_id": 0,
    "price_id": 4010,
    "amount": 350,
    "id": 127,
    "item_type": 5
  },
  {
    "item_id": 0,
    "price_id": 4011,
    "amount": 600,
    "id": 128,
    "item_type": 5
  },
  {
    "item_id": 0,
    "price_id": 4012,
    "amount": 1250,
    "id": 129,
    "item_type": 5
  },
  {
    "item_id": 0,
    "price_id": 4013,
    "amount": 1950,
    "id": 130,
    "item_type": 5
  },
  {
    "item_id": 0,
    "price_id": 4014,
    "amount": 2150,
    "id": 131,
    "item_type": 5
  },
  {
    "item_id": 0,
    "price_id": 4015,
    "amount": 75,
    "id": 132,
    "item_type": 5
  },
  {
    "item_id": 0,
    "price_id": 4016,
    "amount": 150,
    "id": 133,
    "item_type": 5
  },
  {
    "item_id": 0,
    "price_id": 4017,
    "amount": 750,
    "id": 134,
    "item_type": 5
  },
  {
    "item_id": 0,
    "price_id": 4018,
    "amount": 1250,
    "id": 135,
    "item_type": 5
  },
  {
    "item_id": 0,
    "price_id": 4019,
    "amount": 1500,
    "id": 136,
    "item_type": 5
  },
  {
    "item_id": 0,
    "price_id": 4020,
    "amount": 1750,
    "id": 137,
    "item_type": 5
  },
  {
    "item_id": 0,
    "price_id": 4021,
    "amount": 2750,
    "id": 138,
    "item_type": 5
  },
  {
    "item_id": 1,
    "price_id": 999111,
    "amount": 1,
    "id": 139,
    "item_type": 6
  },
  {
    "item_id": 1,
    "price_id": 999112,
    "amount": 2,
    "id": 140,
    "item_type": 6
  },
  {
    "item_id": 1,
    "price_id": 999113,
    "amount": 3,
    "id": 141,
    "item_type": 6
  },
  {
    "item_id": 1,
    "price_id": 999114,
    "amount": 4,
    "id": 142,
    "item_type": 6
  },
  {
    "item_id": 1,
    "price_id": 999115,
    "amount": 5,
    "id": 143,
    "item_type": 6
  },
  {
    "item_id": 1,
    "price_id": 999116,
    "amount": 10,
    "id": 144,
    "item_type": 6
  },
  {
    "item_id": 1,
    "price_id": 999117,
    "amount": 15,
    "id": 145,
    "item_type": 6
  },
  {
    "item_id": 1,
    "price_id": 999118,
    "amount": 20,
    "id": 146,
    "item_type": 6
  },
  {
    "item_id": 1,
    "price_id": 999119,
    "amount": 25,
    "id": 147,
    "item_type": 6
  },
  {
    "item_id": 1,
    "price_id": 999120,
    "amount": 30,
    "id": 148,
    "item_type": 6
  },
  {
    "item_id": 1,
    "price_id": 999121,
    "amount": 35,
    "id": 149,
    "item_type": 6
  },
  {
    "item_id": 1,
    "price_id": 999122,
    "amount": 40,
    "id": 150,
    "item_type": 6
  },
  {
    "item_id": 1,
    "price_id": 999123,
    "amount": 45,
    "id": 151,
    "item_type": 6
  },
  {
    "item_id": 1,
    "price_id": 999124,
    "amount": 50,
    "id": 152,
    "item_type": 6
  },
  {
    "item_id": 1,
    "price_id": 999125,
    "amount": 55,
    "id": 153,
    "item_type": 6
  },
  {
    "item_id": 1,
    "price_id": 999126,
    "amount": 60,
    "id": 154,
    "item_type": 6
  },
  {
    "item_id": 1,
    "price_id": 999127,
    "amount": 65,
    "id": 155,
    "item_type": 6
  },
  {
    "item_id": 1,
    "price_id": 999128,
    "amount": 70,
    "id": 156,
    "item_type": 6
  },
  {
    "item_id": 1,
    "price_id": 999129,
    "amount": 75,
    "id": 157,
    "item_type": 6
  },
  {
    "item_id": 1,
    "price_id": 999130,
    "amount": 80,
    "id": 158,
    "item_type": 6
  },
  {
    "item_id": 1,
    "price_id": 999131,
    "amount": 85,
    "id": 159,
    "item_type": 6
  },
  {
    "item_id": 1,
    "price_id": 999132,
    "amount": 90,
    "id": 160,
    "item_type": 6
  },
  {
    "item_id": 1,
    "price_id": 999133,
    "amount": 95,
    "id": 161,
    "item_type": 6
  },
  {
    "item_id": 1,
    "price_id": 999134,
    "amount": 100,
    "id": 162,
    "item_type": 6
  },
  {
    "item_id": 1,
    "price_id": 999135,
    "amount": 110,
    "id": 163,
    "item_type": 6
  },
  {
    "item_id": 1,
    "price_id": 999136,
    "amount": 120,
    "id": 164,
    "item_type": 6
  },
  {
    "item_id": 1,
    "price_id": 999137,
    "amount": 130,
    "id": 165,
    "item_type": 6
  },
  {
    "item_id": 1,
    "price_id": 999138,
    "amount": 140,
    "id": 166,
    "item_type": 6
  },
  {
    "item_id": 1,
    "price_id": 999139,
    "amount": 150,
    "id": 167,
    "item_type": 6
  },
  {
    "item_id": 1,
    "price_id": 999140,
    "amount": 160,
    "id": 168,
    "item_type": 6
  },
  {
    "item_id": 1,
    "price_id": 999141,
    "amount": 170,
    "id": 169,
    "item_type": 6
  },
  {
    "item_id": 1,
    "price_id": 999142,
    "amount": 180,
    "id": 170,
    "item_type": 6
  },
  {
    "item_id": 1,
    "price_id": 999143,
    "amount": 190,
    "id": 171,
    "item_type": 6
  },
  {
    "item_id": 1,
    "price_id": 999144,
    "amount": 200,
    "id": 172,
    "item_type": 6
  },
  {
    "item_id": 1,
    "price_id": 999145,
    "amount": 210,
    "id": 173,
    "item_type": 6
  },
  {
    "item_id": 1,
    "price_id": 999146,
    "amount": 220,
    "id": 174,
    "item_type": 6
  },
  {
    "item_id": 1,
    "price_id": 999147,
    "amount": 230,
    "id": 175,
    "item_type": 6
  },
  {
    "item_id": 1,
    "price_id": 999148,
    "amount": 240,
    "id": 176,
    "item_type": 6
  },
  {
    "item_id": 1,
    "price_id": 999149,
    "amount": 250,
    "id": 177,
    "item_type": 6
  },
  {
    "item_id": 1,
    "price_id": 999150,
    "amount": 260,
    "id": 178,
    "item_type": 6
  },
  {
    "item_id": 1,
    "price_id": 999151,
    "amount": 270,
    "id": 179,
    "item_type": 6
  },
  {
    "item_id": 1,
    "price_id": 999152,
    "amount": 280,
    "id": 180,
    "item_type": 6
  },
  {
    "item_id": 1,
    "price_id": 999153,
    "amount": 290,
    "id": 181,
    "item_type": 6
  },
  {
    "item_id": 1,
    "price_id": 999154,
    "amount": 300,
    "id": 182,
    "item_type": 6
  },
  {
    "item_id": 1,
    "price_id": 999155,
    "amount": 310,
    "id": 183,
    "item_type": 6
  },
  {
    "item_id": 1,
    "price_id": 999156,
    "amount": 320,
    "id": 184,
    "item_type": 6
  },
  {
    "item_id": 1,
    "price_id": 999157,
    "amount": 330,
    "id": 185,
    "item_type": 6
  },
  {
    "item_id": 1,
    "price_id": 999158,
    "amount": 340,
    "id": 186,
    "item_type": 6
  },
  {
    "item_id": 1,
    "price_id": 999159,
    "amount": 350,
    "id": 187,
    "item_type": 6
  },
  {
    "item_id": 1,
    "price_id": 999160,
    "amount": 360,
    "id": 188,
    "item_type": 6
  },
  {
    "item_id": 1,
    "price_id": 999161,
    "amount": 370,
    "id": 189,
    "item_type": 6
  },
  {
    "item_id": 1,
    "price_id": 999162,
    "amount": 380,
    "id": 190,
    "item_type": 6
  },
  {
    "item_id": 1,
    "price_id": 999163,
    "amount": 390,
    "id": 191,
    "item_type": 6
  },
  {
    "item_id": 1,
    "price_id": 999164,
    "amount": 400,
    "id": 192,
    "item_type": 6
  },
  {
    "item_id": 1,
    "price_id": 999165,
    "amount": 410,
    "id": 193,
    "item_type": 6
  },
  {
    "item_id": 1,
    "price_id": 999166,
    "amount": 420,
    "id": 194,
    "item_type": 6
  },
  {
    "item_id": 1,
    "price_id": 999167,
    "amount": 430,
    "id": 195,
    "item_type": 6
  },
  {
    "item_id": 1,
    "price_id": 999168,
    "amount": 440,
    "id": 196,
    "item_type": 6
  },
  {
    "item_id": 1,
    "price_id": 999169,
    "amount": 450,
    "id": 197,
    "item_type": 6
  },
  {
    "item_id": 1,
    "price_id": 999170,
    "amount": 460,
    "id": 198,
    "item_type": 6
  },
  {
    "item_id": 1,
    "price_id": 999171,
    "amount": 470,
    "id": 199,
    "item_type": 6
  },
  {
    "item_id": 1,
    "price_id": 999172,
    "amount": 480,
    "id": 200,
    "item_type": 6
  },
  {
    "item_id": 1,
    "price_id": 999173,
    "amount": 490,
    "id": 201,
    "item_type": 6
  },
  {
    "item_id": 1,
    "price_id": 999174,
    "amount": 500,
    "id": 202,
    "item_type": 6
  },
  {
    "item_id": 1,
    "price_id": 999175,
    "amount": 510,
    "id": 203,
    "item_type": 6
  },
  {
    "item_id": 1,
    "price_id": 999176,
    "amount": 520,
    "id": 204,
    "item_type": 6
  },
  {
    "item_id": 1,
    "price_id": 999177,
    "amount": 530,
    "id": 205,
    "item_type": 6
  },
  {
    "item_id": 1,
    "price_id": 999178,
    "amount": 540,
    "id": 206,
    "item_type": 6
  },
  {
    "item_id": 1,
    "price_id": 999179,
    "amount": 550,
    "id": 207,
    "item_type": 6
  },
  {
    "item_id": 1,
    "price_id": 999180,
    "amount": 560,
    "id": 208,
    "item_type": 6
  },
  {
    "item_id": 1,
    "price_id": 999181,
    "amount": 570,
    "id": 209,
    "item_type": 6
  },
  {
    "item_id": 1,
    "price_id": 999182,
    "amount": 580,
    "id": 210,
    "item_type": 6
  },
  {
    "item_id": 1,
    "price_id": 999183,
    "amount": 590,
    "id": 211,
    "item_type": 6
  },
  {
    "item_id": 1,
    "price_id": 999184,
    "amount": 600,
    "id": 212,
    "item_type": 6
  },
  {
    "item_id": 1,
    "price_id": 999185,
    "amount": 610,
    "id": 213,
    "item_type": 6
  },
  {
    "item_id": 1,
    "price_id": 999186,
    "amount": 620,
    "id": 214,
    "item_type": 6
  },
  {
    "item_id": 1,
    "price_id": 999187,
    "amount": 630,
    "id": 215,
    "item_type": 6
  },
  {
    "item_id": 1,
    "price_id": 999188,
    "amount": 640,
    "id": 216,
    "item_type": 6
  },
  {
    "item_id": 1,
    "price_id": 999189,
    "amount": 650,
    "id": 217,
    "item_type": 6
  },
  {
    "item_id": 1,
    "price_id": 999190,
    "amount": 660,
    "id": 218,
    "item_type": 6
  },
  {
    "item_id": 1,
    "price_id": 999191,
    "amount": 670,
    "id": 219,
    "item_type": 6
  },
  {
    "item_id": 1,
    "price_id": 999192,
    "amount": 680,
    "id": 220,
    "item_type": 6
  },
  {
    "item_id": 1,
    "price_id": 999193,
    "amount": 690,
    "id": 221,
    "item_type": 6
  },
  {
    "item_id": 1,
    "price_id": 999194,
    "amount": 700,
    "id": 222,
    "item_type": 6
  },
  {
    "item_id": 1,
    "price_id": 999195,
    "amount": 710,
    "id": 223,
    "item_type": 6
  },
  {
    "item_id": 1,
    "price_id": 999196,
    "amount": 720,
    "id": 224,
    "item_type": 6
  },
  {
    "item_id": 1,
    "price_id": 999197,
    "amount": 730,
    "id": 225,
    "item_type": 6
  },
  {
    "item_id": 1,
    "price_id": 999198,
    "amount": 740,
    "id": 226,
    "item_type": 6
  },
  {
    "item_id": 1,
    "price_id": 999199,
    "amount": 750,
    "id": 227,
    "item_type": 6
  },
  {
    "item_id": 1,
    "price_id": 999200,
    "amount": 760,
    "id": 228,
    "item_type": 6
  },
  {
    "item_id": 1,
    "price_id": 999201,
    "amount": 770,
    "id": 229,
    "item_type": 6
  },
  {
    "item_id": 1,
    "price_id": 999202,
    "amount": 780,
    "id": 230,
    "item_type": 6
  },
  {
    "item_id": 1,
    "price_id": 999203,
    "amount": 790,
    "id": 231,
    "item_type": 6
  },
  {
    "item_id": 1,
    "price_id": 999204,
    "amount": 800,
    "id": 232,
    "item_type": 6
  },
  {
    "item_id": 1,
    "price_id": 999205,
    "amount": 810,
    "id": 233,
    "item_type": 6
  },
  {
    "item_id": 1,
    "price_id": 999206,
    "amount": 820,
    "id": 234,
    "item_type": 6
  },
  {
    "item_id": 1,
    "price_id": 999207,
    "amount": 830,
    "id": 235,
    "item_type": 6
  },
  {
    "item_id": 1,
    "price_id": 999208,
    "amount": 840,
    "id": 236,
    "item_type": 6
  },
  {
    "item_id": 1,
    "price_id": 999209,
    "amount": 850,
    "id": 237,
    "item_type": 6
  },
  {
    "item_id": 1,
    "price_id": 999210,
    "amount": 860,
    "id": 238,
    "item_type": 6
  },
  {
    "item_id": 1,
    "price_id": 999211,
    "amount": 870,
    "id": 239,
    "item_type": 6
  },
  {
    "item_id": 1,
    "price_id": 999212,
    "amount": 880,
    "id": 240,
    "item_type": 6
  },
  {
    "item_id": 1,
    "price_id": 999213,
    "amount": 890,
    "id": 241,
    "item_type": 6
  },
  {
    "item_id": 1,
    "price_id": 999214,
    "amount": 900,
    "id": 242,
    "item_type": 6
  },
  {
    "item_id": 1,
    "price_id": 999215,
    "amount": 910,
    "id": 243,
    "item_type": 6
  },
  {
    "item_id": 1,
    "price_id": 999216,
    "amount": 920,
    "id": 244,
    "item_type": 6
  },
  {
    "item_id": 1,
    "price_id": 999217,
    "amount": 930,
    "id": 245,
    "item_type": 6
  },
  {
    "item_id": 1,
    "price_id": 999218,
    "amount": 940,
    "id": 246,
    "item_type": 6
  },
  {
    "item_id": 1,
    "price_id": 999219,
    "amount": 950,
    "id": 247,
    "item_type": 6
  },
  {
    "item_id": 1,
    "price_id": 999220,
    "amount": 960,
    "id": 248,
    "item_type": 6
  },
  {
    "item_id": 1,
    "price_id": 999221,
    "amount": 970,
    "id": 249,
    "item_type": 6
  },
  {
    "item_id": 1,
    "price_id": 999222,
    "amount": 980,
    "id": 250,
    "item_type": 6
  },
  {
    "item_id": 1,
    "price_id": 999223,
    "amount": 990,
    "id": 251,
    "item_type": 6
  },
  {
    "item_id": 1,
    "price_id": 999224,
    "amount": 1000,
    "id": 252,
    "item_type": 6
  },
  {
    "item_id": 1,
    "price_id": 999225,
    "amount": 1010,
    "id": 253,
    "item_type": 6
  },
  {
    "item_id": 1,
    "price_id": 999226,
    "amount": 1020,
    "id": 254,
    "item_type": 6
  },
  {
    "item_id": 1,
    "price_id": 999227,
    "amount": 1030,
    "id": 255,
    "item_type": 6
  },
  {
    "item_id": 1,
    "price_id": 999228,
    "amount": 1040,
    "id": 256,
    "item_type": 6
  },
  {
    "item_id": 1,
    "price_id": 999229,
    "amount": 1050,
    "id": 257,
    "item_type": 6
  },
  {
    "item_id": 1,
    "price_id": 999230,
    "amount": 1060,
    "id": 258,
    "item_type": 6
  },
  {
    "item_id": 1,
    "price_id": 999231,
    "amount": 1070,
    "id": 259,
    "item_type": 6
  },
  {
    "item_id": 1,
    "price_id": 999232,
    "amount": 1080,
    "id": 260,
    "item_type": 6
  },
  {
    "item_id": 1,
    "price_id": 999233,
    "amount": 1090,
    "id": 261,
    "item_type": 6
  },
  {
    "item_id": 1,
    "price_id": 999234,
    "amount": 1100,
    "id": 262,
    "item_type": 6
  },
  {
    "item_id": 1,
    "price_id": 999235,
    "amount": 1110,
    "id": 263,
    "item_type": 6
  },
  {
    "item_id": 1,
    "price_id": 999236,
    "amount": 1120,
    "id": 264,
    "item_type": 6
  },
  {
    "item_id": 1,
    "price_id": 999237,
    "amount": 1130,
    "id": 265,
    "item_type": 6
  },
  {
    "item_id": 1,
    "price_id": 999238,
    "amount": 1140,
    "id": 266,
    "item_type": 6
  },
  {
    "item_id": 1,
    "price_id": 999239,
    "amount": 1150,
    "id": 267,
    "item_type": 6
  },
  {
    "item_id": 1,
    "price_id": 999240,
    "amount": 1160,
    "id": 268,
    "item_type": 6
  },
  {
    "item_id": 1,
    "price_id": 999241,
    "amount": 1170,
    "id": 269,
    "item_type": 6
  },
  {
    "item_id": 1,
    "price_id": 999242,
    "amount": 1180,
    "id": 270,
    "item_type": 6
  },
  {
    "item_id": 1,
    "price_id": 999243,
    "amount": 1190,
    "id": 271,
    "item_type": 6
  },
  {
    "item_id": 1,
    "price_id": 999244,
    "amount": 1200,
    "id": 272,
    "item_type": 6
  },
  {
    "item_id": 1,
    "price_id": 999245,
    "amount": 1210,
    "id": 273,
    "item_type": 6
  },
  {
    "item_id": 1,
    "price_id": 999246,
    "amount": 1220,
    "id": 274,
    "item_type": 6
  },
  {
    "item_id": 1,
    "price_id": 999247,
    "amount": 1230,
    "id": 275,
    "item_type": 6
  },
  {
    "item_id": 1,
    "price_id": 999248,
    "amount": 1240,
    "id": 276,
    "item_type": 6
  },
  {
    "item_id": 1,
    "price_id": 999249,
    "amount": 1250,
    "id": 277,
    "item_type": 6
  },
  {
    "item_id": 1,
    "price_id": 999250,
    "amount": 1260,
    "id": 278,
    "item_type": 6
  },
  {
    "item_id": 1,
    "price_id": 999251,
    "amount": 1270,
    "id": 279,
    "item_type": 6
  },
  {
    "item_id": 1,
    "price_id": 999252,
    "amount": 1280,
    "id": 280,
    "item_type": 6
  },
  {
    "item_id": 1,
    "price_id": 999253,
    "amount": 1290,
    "id": 281,
    "item_type": 6
  },
  {
    "item_id": 1,
    "price_id": 999254,
    "amount": 1300,
    "id": 282,
    "item_type": 6
  },
  {
    "item_id": 1,
    "price_id": 999255,
    "amount": 1310,
    "id": 283,
    "item_type": 6
  },
  {
    "item_id": 1,
    "price_id": 999256,
    "amount": 1320,
    "id": 284,
    "item_type": 6
  },
  {
    "item_id": 1,
    "price_id": 999257,
    "amount": 1330,
    "id": 285,
    "item_type": 6
  },
  {
    "item_id": 1,
    "price_id": 999258,
    "amount": 1340,
    "id": 286,
    "item_type": 6
  },
  {
    "item_id": 1,
    "price_id": 999259,
    "amount": 1350,
    "id": 287,
    "item_type": 6
  },
  {
    "item_id": 1,
    "price_id": 999260,
    "amount": 1360,
    "id": 288,
    "item_type": 6
  },
  {
    "item_id": 1,
    "price_id": 999261,
    "amount": 1370,
    "id": 289,
    "item_type": 6
  },
  {
    "item_id": 1,
    "price_id": 999262,
    "amount": 1380,
    "id": 290,
    "item_type": 6
  },
  {
    "item_id": 1,
    "price_id": 999263,
    "amount": 1390,
    "id": 291,
    "item_type": 6
  },
  {
    "item_id": 1,
    "price_id": 999264,
    "amount": 1400,
    "id": 292,
    "item_type": 6
  },
  {
    "item_id": 1,
    "price_id": 999265,
    "amount": 1410,
    "id": 293,
    "item_type": 6
  },
  {
    "item_id": 1,
    "price_id": 999266,
    "amount": 1420,
    "id": 294,
    "item_type": 6
  },
  {
    "item_id": 1,
    "price_id": 999267,
    "amount": 1430,
    "id": 295,
    "item_type": 6
  },
  {
    "item_id": 1,
    "price_id": 999268,
    "amount": 1440,
    "id": 296,
    "item_type": 6
  },
  {
    "item_id": 1,
    "price_id": 999269,
    "amount": 1450,
    "id": 297,
    "item_type": 6
  },
  {
    "item_id": 1,
    "price_id": 999270,
    "amount": 1460,
    "id": 298,
    "item_type": 6
  },
  {
    "item_id": 2,
    "price_id": 999271,
    "amount": 1,
    "id": 299,
    "item_type": 6
  },
  {
    "item_id": 2,
    "price_id": 999272,
    "amount": 2,
    "id": 300,
    "item_type": 6
  },
  {
    "item_id": 2,
    "price_id": 999273,
    "amount": 3,
    "id": 301,
    "item_type": 6
  },
  {
    "item_id": 2,
    "price_id": 999274,
    "amount": 4,
    "id": 302,
    "item_type": 6
  },
  {
    "item_id": 2,
    "price_id": 999275,
    "amount": 5,
    "id": 303,
    "item_type": 6
  },
  {
    "item_id": 2,
    "price_id": 999276,
    "amount": 10,
    "id": 304,
    "item_type": 6
  },
  {
    "item_id": 2,
    "price_id": 999277,
    "amount": 15,
    "id": 305,
    "item_type": 6
  },
  {
    "item_id": 2,
    "price_id": 999278,
    "amount": 20,
    "id": 306,
    "item_type": 6
  },
  {
    "item_id": 2,
    "price_id": 999279,
    "amount": 25,
    "id": 307,
    "item_type": 6
  },
  {
    "item_id": 2,
    "price_id": 999280,
    "amount": 30,
    "id": 308,
    "item_type": 6
  },
  {
    "item_id": 2,
    "price_id": 999281,
    "amount": 35,
    "id": 309,
    "item_type": 6
  },
  {
    "item_id": 2,
    "price_id": 999282,
    "amount": 40,
    "id": 310,
    "item_type": 6
  },
  {
    "item_id": 2,
    "price_id": 999283,
    "amount": 45,
    "id": 311,
    "item_type": 6
  },
  {
    "item_id": 2,
    "price_id": 999284,
    "amount": 50,
    "id": 312,
    "item_type": 6
  },
  {
    "item_id": 2,
    "price_id": 999285,
    "amount": 55,
    "id": 313,
    "item_type": 6
  },
  {
    "item_id": 2,
    "price_id": 999286,
    "amount": 60,
    "id": 314,
    "item_type": 6
  },
  {
    "item_id": 2,
    "price_id": 999287,
    "amount": 65,
    "id": 315,
    "item_type": 6
  },
  {
    "item_id": 2,
    "price_id": 999288,
    "amount": 70,
    "id": 316,
    "item_type": 6
  },
  {
    "item_id": 2,
    "price_id": 999289,
    "amount": 75,
    "id": 317,
    "item_type": 6
  },
  {
    "item_id": 2,
    "price_id": 999290,
    "amount": 80,
    "id": 318,
    "item_type": 6
  },
  {
    "item_id": 2,
    "price_id": 999291,
    "amount": 85,
    "id": 319,
    "item_type": 6
  },
  {
    "item_id": 2,
    "price_id": 999292,
    "amount": 90,
    "id": 320,
    "item_type": 6
  },
  {
    "item_id": 2,
    "price_id": 999293,
    "amount": 95,
    "id": 321,
    "item_type": 6
  },
  {
    "item_id": 2,
    "price_id": 999294,
    "amount": 100,
    "id": 322,
    "item_type": 6
  },
  {
    "item_id": 2,
    "price_id": 999295,
    "amount": 105,
    "id": 323,
    "item_type": 6
  },
  {
    "item_id": 2,
    "price_id": 999296,
    "amount": 110,
    "id": 324,
    "item_type": 6
  },
  {
    "item_id": 2,
    "price_id": 999297,
    "amount": 115,
    "id": 325,
    "item_type": 6
  },
  {
    "item_id": 2,
    "price_id": 999298,
    "amount": 120,
    "id": 326,
    "item_type": 6
  },
  {
    "item_id": 2,
    "price_id": 999299,
    "amount": 125,
    "id": 327,
    "item_type": 6
  },
  {
    "item_id": 2,
    "price_id": 999300,
    "amount": 130,
    "id": 328,
    "item_type": 6
  },
  {
    "item_id": 2,
    "price_id": 999301,
    "amount": 135,
    "id": 329,
    "item_type": 6
  },
  {
    "item_id": 2,
    "price_id": 999302,
    "amount": 140,
    "id": 330,
    "item_type": 6
  },
  {
    "item_id": 2,
    "price_id": 999303,
    "amount": 145,
    "id": 331,
    "item_type": 6
  },
  {
    "item_id": 2,
    "price_id": 999304,
    "amount": 150,
    "id": 332,
    "item_type": 6
  },
  {
    "item_id": 2,
    "price_id": 999305,
    "amount": 155,
    "id": 333,
    "item_type": 6
  },
  {
    "item_id": 2,
    "price_id": 999306,
    "amount": 160,
    "id": 334,
    "item_type": 6
  },
  {
    "item_id": 2,
    "price_id": 999307,
    "amount": 165,
    "id": 335,
    "item_type": 6
  },
  {
    "item_id": 2,
    "price_id": 999308,
    "amount": 170,
    "id": 336,
    "item_type": 6
  },
  {
    "item_id": 2,
    "price_id": 999309,
    "amount": 175,
    "id": 337,
    "item_type": 6
  },
  {
    "item_id": 2,
    "price_id": 999310,
    "amount": 180,
    "id": 338,
    "item_type": 6
  },
  {
    "item_id": 2,
    "price_id": 999311,
    "amount": 185,
    "id": 339,
    "item_type": 6
  },
  {
    "item_id": 2,
    "price_id": 999312,
    "amount": 190,
    "id": 340,
    "item_type": 6
  },
  {
    "item_id": 2,
    "price_id": 999313,
    "amount": 195,
    "id": 341,
    "item_type": 6
  },
  {
    "item_id": 2,
    "price_id": 999314,
    "amount": 200,
    "id": 342,
    "item_type": 6
  },
  {
    "item_id": 2,
    "price_id": 999315,
    "amount": 205,
    "id": 343,
    "item_type": 6
  },
  {
    "item_id": 2,
    "price_id": 999316,
    "amount": 210,
    "id": 344,
    "item_type": 6
  },
  {
    "item_id": 2,
    "price_id": 999317,
    "amount": 215,
    "id": 345,
    "item_type": 6
  },
  {
    "item_id": 2,
    "price_id": 999318,
    "amount": 220,
    "id": 346,
    "item_type": 6
  },
  {
    "item_id": 2,
    "price_id": 999319,
    "amount": 225,
    "id": 347,
    "item_type": 6
  },
  {
    "item_id": 2,
    "price_id": 999320,
    "amount": 230,
    "id": 348,
    "item_type": 6
  },
  {
    "item_id": 2,
    "price_id": 999321,
    "amount": 235,
    "id": 349,
    "item_type": 6
  },
  {
    "item_id": 2,
    "price_id": 999322,
    "amount": 240,
    "id": 350,
    "item_type": 6
  },
  {
    "item_id": 2,
    "price_id": 999323,
    "amount": 245,
    "id": 351,
    "item_type": 6
  },
  {
    "item_id": 2,
    "price_id": 999324,
    "amount": 250,
    "id": 352,
    "item_type": 6
  },
  {
    "item_id": 2,
    "price_id": 999325,
    "amount": 255,
    "id": 353,
    "item_type": 6
  },
  {
    "item_id": 2,
    "price_id": 999326,
    "amount": 260,
    "id": 354,
    "item_type": 6
  },
  {
    "item_id": 2,
    "price_id": 999327,
    "amount": 265,
    "id": 355,
    "item_type": 6
  },
  {
    "item_id": 2,
    "price_id": 999328,
    "amount": 270,
    "id": 356,
    "item_type": 6
  },
  {
    "item_id": 2,
    "price_id": 999329,
    "amount": 275,
    "id": 357,
    "item_type": 6
  },
  {
    "item_id": 2,
    "price_id": 999330,
    "amount": 280,
    "id": 358,
    "item_type": 6
  },
  {
    "item_id": 2,
    "price_id": 999331,
    "amount": 285,
    "id": 359,
    "item_type": 6
  },
  {
    "item_id": 2,
    "price_id": 999332,
    "amount": 290,
    "id": 360,
    "item_type": 6
  },
  {
    "item_id": 2,
    "price_id": 999333,
    "amount": 295,
    "id": 361,
    "item_type": 6
  },
  {
    "item_id": 2,
    "price_id": 999334,
    "amount": 300,
    "id": 362,
    "item_type": 6
  },
  {
    "item_id": 2,
    "price_id": 999335,
    "amount": 305,
    "id": 363,
    "item_type": 6
  },
  {
    "item_id": 2,
    "price_id": 999336,
    "amount": 310,
    "id": 364,
    "item_type": 6
  },
  {
    "item_id": 2,
    "price_id": 999337,
    "amount": 315,
    "id": 365,
    "item_type": 6
  },
  {
    "item_id": 2,
    "price_id": 999338,
    "amount": 320,
    "id": 366,
    "item_type": 6
  },
  {
    "item_id": 2,
    "price_id": 999339,
    "amount": 325,
    "id": 367,
    "item_type": 6
  },
  {
    "item_id": 2,
    "price_id": 999340,
    "amount": 330,
    "id": 368,
    "item_type": 6
  },
  {
    "item_id": 2,
    "price_id": 999341,
    "amount": 335,
    "id": 369,
    "item_type": 6
  },
  {
    "item_id": 2,
    "price_id": 999342,
    "amount": 340,
    "id": 370,
    "item_type": 6
  },
  {
    "item_id": 2,
    "price_id": 999343,
    "amount": 345,
    "id": 371,
    "item_type": 6
  },
  {
    "item_id": 2,
    "price_id": 999344,
    "amount": 350,
    "id": 372,
    "item_type": 6
  },
  {
    "item_id": 2,
    "price_id": 999345,
    "amount": 355,
    "id": 373,
    "item_type": 6
  },
  {
    "item_id": 2,
    "price_id": 999346,
    "amount": 360,
    "id": 374,
    "item_type": 6
  },
  {
    "item_id": 2,
    "price_id": 999347,
    "amount": 365,
    "id": 375,
    "item_type": 6
  },
  {
    "item_id": 2,
    "price_id": 999348,
    "amount": 370,
    "id": 376,
    "item_type": 6
  },
  {
    "item_id": 2,
    "price_id": 999349,
    "amount": 375,
    "id": 377,
    "item_type": 6
  },
  {
    "item_id": 2,
    "price_id": 999350,
    "amount": 380,
    "id": 378,
    "item_type": 6
  },
  {
    "item_id": 2,
    "price_id": 999351,
    "amount": 385,
    "id": 379,
    "item_type": 6
  },
  {
    "item_id": 2,
    "price_id": 999352,
    "amount": 390,
    "id": 380,
    "item_type": 6
  },
  {
    "item_id": 2,
    "price_id": 999353,
    "amount": 395,
    "id": 381,
    "item_type": 6
  },
  {
    "item_id": 2,
    "price_id": 999354,
    "amount": 400,
    "id": 382,
    "item_type": 6
  },
  {
    "item_id": 2,
    "price_id": 999355,
    "amount": 405,
    "id": 383,
    "item_type": 6
  },
  {
    "item_id": 2,
    "price_id": 999356,
    "amount": 410,
    "id": 384,
    "item_type": 6
  },
  {
    "item_id": 2,
    "price_id": 999357,
    "amount": 415,
    "id": 385,
    "item_type": 6
  },
  {
    "item_id": 2,
    "price_id": 999358,
    "amount": 420,
    "id": 386,
    "item_type": 6
  },
  {
    "item_id": 2,
    "price_id": 999359,
    "amount": 425,
    "id": 387,
    "item_type": 6
  },
  {
    "item_id": 2,
    "price_id": 999360,
    "amount": 430,
    "id": 388,
    "item_type": 6
  },
  {
    "item_id": 2,
    "price_id": 999361,
    "amount": 435,
    "id": 389,
    "item_type": 6
  },
  {
    "item_id": 2,
    "price_id": 999362,
    "amount": 440,
    "id": 390,
    "item_type": 6
  },
  {
    "item_id": 2,
    "price_id": 999363,
    "amount": 445,
    "id": 391,
    "item_type": 6
  },
  {
    "item_id": 2,
    "price_id": 999364,
    "amount": 450,
    "id": 392,
    "item_type": 6
  },
  {
    "item_id": 2,
    "price_id": 999365,
    "amount": 455,
    "id": 393,
    "item_type": 6
  },
  {
    "item_id": 2,
    "price_id": 999366,
    "amount": 460,
    "id": 394,
    "item_type": 6
  },
  {
    "item_id": 2,
    "price_id": 999367,
    "amount": 465,
    "id": 395,
    "item_type": 6
  },
  {
    "item_id": 2,
    "price_id": 999368,
    "amount": 470,
    "id": 396,
    "item_type": 6
  },
  {
    "item_id": 2,
    "price_id": 999369,
    "amount": 475,
    "id": 397,
    "item_type": 6
  },
  {
    "item_id": 2,
    "price_id": 999370,
    "amount": 480,
    "id": 398,
    "item_type": 6
  },
  {
    "item_id": 2,
    "price_id": 999371,
    "amount": 485,
    "id": 399,
    "item_type": 6
  },
  {
    "item_id": 2,
    "price_id": 999372,
    "amount": 490,
    "id": 400,
    "item_type": 6
  },
  {
    "item_id": 2,
    "price_id": 999373,
    "amount": 495,
    "id": 401,
    "item_type": 6
  },
  {
    "item_id": 2,
    "price_id": 999374,
    "amount": 500,
    "id": 402,
    "item_type": 6
  },
  {
    "item_id": 2,
    "price_id": 999375,
    "amount": 505,
    "id": 403,
    "item_type": 6
  },
  {
    "item_id": 2,
    "price_id": 999376,
    "amount": 510,
    "id": 404,
    "item_type": 6
  },
  {
    "item_id": 2,
    "price_id": 999377,
    "amount": 515,
    "id": 405,
    "item_type": 6
  },
  {
    "item_id": 2,
    "price_id": 999378,
    "amount": 520,
    "id": 406,
    "item_type": 6
  },
  {
    "item_id": 2,
    "price_id": 999379,
    "amount": 525,
    "id": 407,
    "item_type": 6
  },
  {
    "item_id": 2,
    "price_id": 999380,
    "amount": 530,
    "id": 408,
    "item_type": 6
  },
  {
    "item_id": 2,
    "price_id": 999381,
    "amount": 535,
    "id": 409,
    "item_type": 6
  },
  {
    "item_id": 2,
    "price_id": 999382,
    "amount": 540,
    "id": 410,
    "item_type": 6
  },
  {
    "item_id": 2,
    "price_id": 999383,
    "amount": 545,
    "id": 411,
    "item_type": 6
  },
  {
    "item_id": 2,
    "price_id": 999384,
    "amount": 550,
    "id": 412,
    "item_type": 6
  },
  {
    "item_id": 2,
    "price_id": 999385,
    "amount": 555,
    "id": 413,
    "item_type": 6
  },
  {
    "item_id": 2,
    "price_id": 999386,
    "amount": 560,
    "id": 414,
    "item_type": 6
  },
  {
    "item_id": 2,
    "price_id": 999387,
    "amount": 565,
    "id": 415,
    "item_type": 6
  },
  {
    "item_id": 2,
    "price_id": 999388,
    "amount": 570,
    "id": 416,
    "item_type": 6
  },
  {
    "item_id": 2,
    "price_id": 999389,
    "amount": 575,
    "id": 417,
    "item_type": 6
  },
  {
    "item_id": 2,
    "price_id": 999390,
    "amount": 580,
    "id": 418,
    "item_type": 6
  },
  {
    "item_id": 2,
    "price_id": 999391,
    "amount": 585,
    "id": 419,
    "item_type": 6
  },
  {
    "item_id": 2,
    "price_id": 999392,
    "amount": 590,
    "id": 420,
    "item_type": 6
  },
  {
    "item_id": 2,
    "price_id": 999393,
    "amount": 595,
    "id": 421,
    "item_type": 6
  },
  {
    "item_id": 2,
    "price_id": 999394,
    "amount": 600,
    "id": 422,
    "item_type": 6
  },
  {
    "item_id": 2,
    "price_id": 999395,
    "amount": 605,
    "id": 423,
    "item_type": 6
  },
  {
    "item_id": 2,
    "price_id": 999396,
    "amount": 610,
    "id": 424,
    "item_type": 6
  },
  {
    "item_id": 2,
    "price_id": 999397,
    "amount": 615,
    "id": 425,
    "item_type": 6
  },
  {
    "item_id": 2,
    "price_id": 999398,
    "amount": 620,
    "id": 426,
    "item_type": 6
  },
  {
    "item_id": 2,
    "price_id": 999399,
    "amount": 625,
    "id": 427,
    "item_type": 6
  },
  {
    "item_id": 2,
    "price_id": 999400,
    "amount": 630,
    "id": 428,
    "item_type": 6
  },
  {
    "item_id": 2,
    "price_id": 999401,
    "amount": 635,
    "id": 429,
    "item_type": 6
  },
  {
    "item_id": 2,
    "price_id": 999402,
    "amount": 640,
    "id": 430,
    "item_type": 6
  },
  {
    "item_id": 2,
    "price_id": 999403,
    "amount": 645,
    "id": 431,
    "item_type": 6
  },
  {
    "item_id": 2,
    "price_id": 999404,
    "amount": 650,
    "id": 432,
    "item_type": 6
  },
  {
    "item_id": 2,
    "price_id": 999405,
    "amount": 655,
    "id": 433,
    "item_type": 6
  },
  {
    "item_id": 2,
    "price_id": 999406,
    "amount": 660,
    "id": 434,
    "item_type": 6
  },
  {
    "item_id": 2,
    "price_id": 999407,
    "amount": 665,
    "id": 435,
    "item_type": 6
  },
  {
    "item_id": 2,
    "price_id": 999408,
    "amount": 670,
    "id": 436,
    "item_type": 6
  },
  {
    "item_id": 2,
    "price_id": 999409,
    "amount": 675,
    "id": 437,
    "item_type": 6
  },
  {
    "item_id": 2,
    "price_id": 999410,
    "amount": 680,
    "id": 438,
    "item_type": 6
  },
  {
    "item_id": 2,
    "price_id": 999411,
    "amount": 685,
    "id": 439,
    "item_type": 6
  },
  {
    "item_id": 2,
    "price_id": 999412,
    "amount": 690,
    "id": 440,
    "item_type": 6
  },
  {
    "item_id": 2,
    "price_id": 999413,
    "amount": 695,
    "id": 441,
    "item_type": 6
  },
  {
    "item_id": 2,
    "price_id": 999414,
    "amount": 700,
    "id": 442,
    "item_type": 6
  },
  {
    "item_id": 2,
    "price_id": 999415,
    "amount": 705,
    "id": 443,
    "item_type": 6
  },
  {
    "item_id": 2,
    "price_id": 999416,
    "amount": 710,
    "id": 444,
    "item_type": 6
  },
  {
    "item_id": 2,
    "price_id": 999417,
    "amount": 715,
    "id": 445,
    "item_type": 6
  },
  {
    "item_id": 2,
    "price_id": 999418,
    "amount": 720,
    "id": 446,
    "item_type": 6
  },
  {
    "item_id": 2,
    "price_id": 999419,
    "amount": 725,
    "id": 447,
    "item_type": 6
  },
  {
    "item_id": 2,
    "price_id": 999420,
    "amount": 730,
    "id": 448,
    "item_type": 6
  },
  {
    "item_id": 2,
    "price_id": 999421,
    "amount": 735,
    "id": 449,
    "item_type": 6
  },
  {
    "item_id": 2,
    "price_id": 999422,
    "amount": 740,
    "id": 450,
    "item_type": 6
  },
  {
    "item_id": 2,
    "price_id": 999423,
    "amount": 745,
    "id": 451,
    "item_type": 6
  },
  {
    "item_id": 2,
    "price_id": 999424,
    "amount": 750,
    "id": 452,
    "item_type": 6
  },
  {
    "item_id": 2,
    "price_id": 999425,
    "amount": 755,
    "id": 453,
    "item_type": 6
  },
  {
    "item_id": 2,
    "price_id": 999426,
    "amount": 760,
    "id": 454,
    "item_type": 6
  },
  {
    "item_id": 2,
    "price_id": 999427,
    "amount": 765,
    "id": 455,
    "item_type": 6
  },
  {
    "item_id": 2,
    "price_id": 999428,
    "amount": 770,
    "id": 456,
    "item_type": 6
  },
  {
    "item_id": 2,
    "price_id": 999429,
    "amount": 775,
    "id": 457,
    "item_type": 6
  },
  {
    "item_id": 2,
    "price_id": 999430,
    "amount": 780,
    "id": 458,
    "item_type": 6
  },
  {
    "item_id": 11,
    "price_id": 999431,
    "amount": 1,
    "id": 459,
    "item_type": 6
  },
  {
    "item_id": 11,
    "price_id": 999432,
    "amount": 2,
    "id": 460,
    "item_type": 6
  },
  {
    "item_id": 11,
    "price_id": 999433,
    "amount": 3,
    "id": 461,
    "item_type": 6
  },
  {
    "item_id": 11,
    "price_id": 999434,
    "amount": 4,
    "id": 462,
    "item_type": 6
  },
  {
    "item_id": 11,
    "price_id": 999435,
    "amount": 5,
    "id": 463,
    "item_type": 6
  },
  {
    "item_id": 11,
    "price_id": 999436,
    "amount": 10,
    "id": 464,
    "item_type": 6
  },
  {
    "item_id": 11,
    "price_id": 999437,
    "amount": 15,
    "id": 465,
    "item_type": 6
  },
  {
    "item_id": 11,
    "price_id": 999438,
    "amount": 20,
    "id": 466,
    "item_type": 6
  },
  {
    "item_id": 11,
    "price_id": 999439,
    "amount": 25,
    "id": 467,
    "item_type": 6
  },
  {
    "item_id": 11,
    "price_id": 999440,
    "amount": 30,
    "id": 468,
    "item_type": 6
  },
  {
    "item_id": 11,
    "price_id": 999441,
    "amount": 35,
    "id": 469,
    "item_type": 6
  },
  {
    "item_id": 11,
    "price_id": 999442,
    "amount": 40,
    "id": 470,
    "item_type": 6
  },
  {
    "item_id": 11,
    "price_id": 999443,
    "amount": 45,
    "id": 471,
    "item_type": 6
  },
  {
    "item_id": 11,
    "price_id": 999444,
    "amount": 50,
    "id": 472,
    "item_type": 6
  },
  {
    "item_id": 11,
    "price_id": 999445,
    "amount": 55,
    "id": 473,
    "item_type": 6
  },
  {
    "item_id": 11,
    "price_id": 999446,
    "amount": 60,
    "id": 474,
    "item_type": 6
  },
  {
    "item_id": 11,
    "price_id": 999447,
    "amount": 65,
    "id": 475,
    "item_type": 6
  },
  {
    "item_id": 11,
    "price_id": 999448,
    "amount": 70,
    "id": 476,
    "item_type": 6
  },
  {
    "item_id": 11,
    "price_id": 999449,
    "amount": 75,
    "id": 477,
    "item_type": 6
  },
  {
    "item_id": 11,
    "price_id": 999450,
    "amount": 80,
    "id": 478,
    "item_type": 6
  },
  {
    "item_id": 11,
    "price_id": 999451,
    "amount": 85,
    "id": 479,
    "item_type": 6
  },
  {
    "item_id": 11,
    "price_id": 999452,
    "amount": 90,
    "id": 480,
    "item_type": 6
  },
  {
    "item_id": 11,
    "price_id": 999453,
    "amount": 95,
    "id": 481,
    "item_type": 6
  },
  {
    "item_id": 11,
    "price_id": 999454,
    "amount": 100,
    "id": 482,
    "item_type": 6
  },
  {
    "item_id": 11,
    "price_id": 999455,
    "amount": 105,
    "id": 483,
    "item_type": 6
  },
  {
    "item_id": 11,
    "price_id": 999456,
    "amount": 110,
    "id": 484,
    "item_type": 6
  },
  {
    "item_id": 11,
    "price_id": 999457,
    "amount": 115,
    "id": 485,
    "item_type": 6
  },
  {
    "item_id": 11,
    "price_id": 999458,
    "amount": 120,
    "id": 486,
    "item_type": 6
  },
  {
    "item_id": 11,
    "price_id": 999459,
    "amount": 125,
    "id": 487,
    "item_type": 6
  },
  {
    "item_id": 11,
    "price_id": 999460,
    "amount": 130,
    "id": 488,
    "item_type": 6
  },
  {
    "item_id": 12,
    "price_id": 999461,
    "amount": 1,
    "id": 489,
    "item_type": 6
  },
  {
    "item_id": 12,
    "price_id": 999462,
    "amount": 2,
    "id": 490,
    "item_type": 6
  },
  {
    "item_id": 12,
    "price_id": 999463,
    "amount": 3,
    "id": 491,
    "item_type": 6
  },
  {
    "item_id": 12,
    "price_id": 999464,
    "amount": 4,
    "id": 492,
    "item_type": 6
  },
  {
    "item_id": 12,
    "price_id": 999465,
    "amount": 5,
    "id": 493,
    "item_type": 6
  },
  {
    "item_id": 12,
    "price_id": 999466,
    "amount": 10,
    "id": 494,
    "item_type": 6
  },
  {
    "item_id": 12,
    "price_id": 999467,
    "amount": 15,
    "id": 495,
    "item_type": 6
  },
  {
    "item_id": 12,
    "price_id": 999468,
    "amount": 20,
    "id": 496,
    "item_type": 6
  },
  {
    "item_id": 12,
    "price_id": 999469,
    "amount": 25,
    "id": 497,
    "item_type": 6
  },
  {
    "item_id": 12,
    "price_id": 999470,
    "amount": 30,
    "id": 498,
    "item_type": 6
  },
  {
    "item_id": 12,
    "price_id": 999471,
    "amount": 35,
    "id": 499,
    "item_type": 6
  },
  {
    "item_id": 12,
    "price_id": 999472,
    "amount": 40,
    "id": 500,
    "item_type": 6
  },
  {
    "item_id": 12,
    "price_id": 999473,
    "amount": 45,
    "id": 501,
    "item_type": 6
  },
  {
    "item_id": 12,
    "price_id": 999474,
    "amount": 50,
    "id": 502,
    "item_type": 6
  },
  {
    "item_id": 12,
    "price_id": 999475,
    "amount": 55,
    "id": 503,
    "item_type": 6
  },
  {
    "item_id": 12,
    "price_id": 999476,
    "amount": 60,
    "id": 504,
    "item_type": 6
  },
  {
    "item_id": 12,
    "price_id": 999477,
    "amount": 65,
    "id": 505,
    "item_type": 6
  },
  {
    "item_id": 12,
    "price_id": 999478,
    "amount": 70,
    "id": 506,
    "item_type": 6
  },
  {
    "item_id": 12,
    "price_id": 999479,
    "amount": 75,
    "id": 507,
    "item_type": 6
  },
  {
    "item_id": 12,
    "price_id": 999480,
    "amount": 80,
    "id": 508,
    "item_type": 6
  },
  {
    "item_id": 12,
    "price_id": 999481,
    "amount": 85,
    "id": 509,
    "item_type": 6
  },
  {
    "item_id": 12,
    "price_id": 999482,
    "amount": 90,
    "id": 510,
    "item_type": 6
  },
  {
    "item_id": 12,
    "price_id": 999483,
    "amount": 95,
    "id": 511,
    "item_type": 6
  },
  {
    "item_id": 12,
    "price_id": 999484,
    "amount": 100,
    "id": 512,
    "item_type": 6
  },
  {
    "item_id": 12,
    "price_id": 999485,
    "amount": 105,
    "id": 513,
    "item_type": 6
  },
  {
    "item_id": 12,
    "price_id": 999486,
    "amount": 110,
    "id": 514,
    "item_type": 6
  },
  {
    "item_id": 12,
    "price_id": 999487,
    "amount": 115,
    "id": 515,
    "item_type": 6
  },
  {
    "item_id": 12,
    "price_id": 999488,
    "amount": 120,
    "id": 516,
    "item_type": 6
  },
  {
    "item_id": 12,
    "price_id": 999489,
    "amount": 125,
    "id": 517,
    "item_type": 6
  },
  {
    "item_id": 12,
    "price_id": 999490,
    "amount": 130,
    "id": 518,
    "item_type": 6
  },
  {
    "item_id": 13,
    "price_id": 999491,
    "amount": 1,
    "id": 519,
    "item_type": 6
  },
  {
    "item_id": 13,
    "price_id": 999492,
    "amount": 2,
    "id": 520,
    "item_type": 6
  },
  {
    "item_id": 13,
    "price_id": 999493,
    "amount": 3,
    "id": 521,
    "item_type": 6
  },
  {
    "item_id": 13,
    "price_id": 999494,
    "amount": 4,
    "id": 522,
    "item_type": 6
  },
  {
    "item_id": 13,
    "price_id": 999495,
    "amount": 5,
    "id": 523,
    "item_type": 6
  },
  {
    "item_id": 13,
    "price_id": 999496,
    "amount": 10,
    "id": 524,
    "item_type": 6
  },
  {
    "item_id": 13,
    "price_id": 999497,
    "amount": 15,
    "id": 525,
    "item_type": 6
  },
  {
    "item_id": 13,
    "price_id": 999498,
    "amount": 20,
    "id": 526,
    "item_type": 6
  },
  {
    "item_id": 13,
    "price_id": 999499,
    "amount": 25,
    "id": 527,
    "item_type": 6
  },
  {
    "item_id": 13,
    "price_id": 999500,
    "amount": 30,
    "id": 528,
    "item_type": 6
  },
  {
    "item_id": 13,
    "price_id": 999501,
    "amount": 35,
    "id": 529,
    "item_type": 6
  },
  {
    "item_id": 13,
    "price_id": 999502,
    "amount": 40,
    "id": 530,
    "item_type": 6
  },
  {
    "item_id": 13,
    "price_id": 999503,
    "amount": 45,
    "id": 531,
    "item_type": 6
  },
  {
    "item_id": 13,
    "price_id": 999504,
    "amount": 50,
    "id": 532,
    "item_type": 6
  },
  {
    "item_id": 13,
    "price_id": 999505,
    "amount": 55,
    "id": 533,
    "item_type": 6
  },
  {
    "item_id": 13,
    "price_id": 999506,
    "amount": 60,
    "id": 534,
    "item_type": 6
  },
  {
    "item_id": 13,
    "price_id": 999507,
    "amount": 65,
    "id": 535,
    "item_type": 6
  },
  {
    "item_id": 13,
    "price_id": 999508,
    "amount": 70,
    "id": 536,
    "item_type": 6
  },
  {
    "item_id": 13,
    "price_id": 999509,
    "amount": 75,
    "id": 537,
    "item_type": 6
  },
  {
    "item_id": 13,
    "price_id": 999510,
    "amount": 80,
    "id": 538,
    "item_type": 6
  },
  {
    "item_id": 13,
    "price_id": 999511,
    "amount": 85,
    "id": 539,
    "item_type": 6
  },
  {
    "item_id": 13,
    "price_id": 999512,
    "amount": 90,
    "id": 540,
    "item_type": 6
  },
  {
    "item_id": 13,
    "price_id": 999513,
    "amount": 95,
    "id": 541,
    "item_type": 6
  },
  {
    "item_id": 13,
    "price_id": 999514,
    "amount": 100,
    "id": 542,
    "item_type": 6
  },
  {
    "item_id": 13,
    "price_id": 999515,
    "amount": 105,
    "id": 543,
    "item_type": 6
  },
  {
    "item_id": 13,
    "price_id": 999516,
    "amount": 110,
    "id": 544,
    "item_type": 6
  },
  {
    "item_id": 13,
    "price_id": 999517,
    "amount": 115,
    "id": 545,
    "item_type": 6
  },
  {
    "item_id": 13,
    "price_id": 999518,
    "amount": 120,
    "id": 546,
    "item_type": 6
  },
  {
    "item_id": 13,
    "price_id": 999519,
    "amount": 125,
    "id": 547,
    "item_type": 6
  },
  {
    "item_id": 13,
    "price_id": 999520,
    "amount": 130,
    "id": 548,
    "item_type": 6
  },
  {
    "item_id": 14,
    "price_id": 999521,
    "amount": 1,
    "id": 549,
    "item_type": 6
  },
  {
    "item_id": 14,
    "price_id": 999522,
    "amount": 2,
    "id": 550,
    "item_type": 6
  },
  {
    "item_id": 14,
    "price_id": 999523,
    "amount": 3,
    "id": 551,
    "item_type": 6
  },
  {
    "item_id": 14,
    "price_id": 999524,
    "amount": 4,
    "id": 552,
    "item_type": 6
  },
  {
    "item_id": 14,
    "price_id": 999525,
    "amount": 5,
    "id": 553,
    "item_type": 6
  },
  {
    "item_id": 14,
    "price_id": 999526,
    "amount": 10,
    "id": 554,
    "item_type": 6
  },
  {
    "item_id": 14,
    "price_id": 999527,
    "amount": 15,
    "id": 555,
    "item_type": 6
  },
  {
    "item_id": 14,
    "price_id": 999528,
    "amount": 20,
    "id": 556,
    "item_type": 6
  },
  {
    "item_id": 14,
    "price_id": 999529,
    "amount": 25,
    "id": 557,
    "item_type": 6
  },
  {
    "item_id": 14,
    "price_id": 999530,
    "amount": 30,
    "id": 558,
    "item_type": 6
  },
  {
    "item_id": 14,
    "price_id": 999531,
    "amount": 35,
    "id": 559,
    "item_type": 6
  },
  {
    "item_id": 14,
    "price_id": 999532,
    "amount": 40,
    "id": 560,
    "item_type": 6
  },
  {
    "item_id": 14,
    "price_id": 999533,
    "amount": 45,
    "id": 561,
    "item_type": 6
  },
  {
    "item_id": 14,
    "price_id": 999534,
    "amount": 50,
    "id": 562,
    "item_type": 6
  },
  {
    "item_id": 14,
    "price_id": 999535,
    "amount": 55,
    "id": 563,
    "item_type": 6
  },
  {
    "item_id": 14,
    "price_id": 999536,
    "amount": 60,
    "id": 564,
    "item_type": 6
  },
  {
    "item_id": 14,
    "price_id": 999537,
    "amount": 65,
    "id": 565,
    "item_type": 6
  },
  {
    "item_id": 14,
    "price_id": 999538,
    "amount": 70,
    "id": 566,
    "item_type": 6
  },
  {
    "item_id": 14,
    "price_id": 999539,
    "amount": 75,
    "id": 567,
    "item_type": 6
  },
  {
    "item_id": 14,
    "price_id": 999540,
    "amount": 80,
    "id": 568,
    "item_type": 6
  },
  {
    "item_id": 14,
    "price_id": 999541,
    "amount": 85,
    "id": 569,
    "item_type": 6
  },
  {
    "item_id": 14,
    "price_id": 999542,
    "amount": 90,
    "id": 570,
    "item_type": 6
  },
  {
    "item_id": 14,
    "price_id": 999543,
    "amount": 95,
    "id": 571,
    "item_type": 6
  },
  {
    "item_id": 14,
    "price_id": 999544,
    "amount": 100,
    "id": 572,
    "item_type": 6
  },
  {
    "item_id": 14,
    "price_id": 999545,
    "amount": 105,
    "id": 573,
    "item_type": 6
  },
  {
    "item_id": 14,
    "price_id": 999546,
    "amount": 110,
    "id": 574,
    "item_type": 6
  },
  {
    "item_id": 14,
    "price_id": 999547,
    "amount": 115,
    "id": 575,
    "item_type": 6
  },
  {
    "item_id": 14,
    "price_id": 999548,
    "amount": 120,
    "id": 576,
    "item_type": 6
  },
  {
    "item_id": 14,
    "price_id": 999549,
    "amount": 125,
    "id": 577,
    "item_type": 6
  },
  {
    "item_id": 14,
    "price_id": 999550,
    "amount": 130,
    "id": 578,
    "item_type": 6
  },
  {
    "item_id": 99,
    "price_id": 999551,
    "amount": 1,
    "id": 579,
    "item_type": 6
  },
  {
    "item_id": 99,
    "price_id": 999552,
    "amount": 2,
    "id": 580,
    "item_type": 6
  },
  {
    "item_id": 99,
    "price_id": 999553,
    "amount": 3,
    "id": 581,
    "item_type": 6
  },
  {
    "item_id": 99,
    "price_id": 999554,
    "amount": 5,
    "id": 582,
    "item_type": 6
  },
  {
    "item_id": 99,
    "price_id": 999555,
    "amount": 10,
    "id": 583,
    "item_type": 6
  },
  {
    "item_id": 99,
    "price_id": 999556,
    "amount": 15,
    "id": 584,
    "item_type": 6
  },
  {
    "item_id": 99,
    "price_id": 999557,
    "amount": 20,
    "id": 585,
    "item_type": 6
  },
  {
    "item_id": 99,
    "price_id": 999558,
    "amount": 25,
    "id": 586,
    "item_type": 6
  },
  {
    "item_id": 99,
    "price_id": 999559,
    "amount": 30,
    "id": 587,
    "item_type": 6
  },
  {
    "item_id": 99,
    "price_id": 999560,
    "amount": 35,
    "id": 588,
    "item_type": 6
  },
  {
    "item_id": 99,
    "price_id": 999561,
    "amount": 40,
    "id": 589,
    "item_type": 6
  },
  {
    "item_id": 99,
    "price_id": 999562,
    "amount": 45,
    "id": 590,
    "item_type": 6
  },
  {
    "item_id": 99,
    "price_id": 999563,
    "amount": 50,
    "id": 591,
    "item_type": 6
  },
  {
    "item_id": 99,
    "price_id": 999564,
    "amount": 55,
    "id": 592,
    "item_type": 6
  },
  {
    "item_id": 99,
    "price_id": 999565,
    "amount": 60,
    "id": 593,
    "item_type": 6
  },
  {
    "item_id": 99,
    "price_id": 999566,
    "amount": 65,
    "id": 594,
    "item_type": 6
  },
  {
    "item_id": 99,
    "price_id": 999567,
    "amount": 70,
    "id": 595,
    "item_type": 6
  },
  {
    "item_id": 99,
    "price_id": 999568,
    "amount": 75,
    "id": 596,
    "item_type": 6
  },
  {
    "item_id": 99,
    "price_id": 999569,
    "amount": 80,
    "id": 597,
    "item_type": 6
  },
  {
    "item_id": 99,
    "price_id": 999570,
    "amount": 85,
    "id": 598,
    "item_type": 6
  },
  {
    "item_id": 99,
    "price_id": 999571,
    "amount": 90,
    "id": 599,
    "item_type": 6
  },
  {
    "item_id": 99,
    "price_id": 999572,
    "amount": 95,
    "id": 600,
    "item_type": 6
  },
  {
    "item_id": 99,
    "price_id": 999573,
    "amount": 100,
    "id": 601,
    "item_type": 6
  },
  {
    "item_id": 99,
    "price_id": 999574,
    "amount": 105,
    "id": 602,
    "item_type": 6
  },
  {
    "item_id": 99,
    "price_id": 999575,
    "amount": 110,
    "id": 603,
    "item_type": 6
  },
  {
    "item_id": 99,
    "price_id": 999576,
    "amount": 115,
    "id": 604,
    "item_type": 6
  },
  {
    "item_id": 99,
    "price_id": 999577,
    "amount": 120,
    "id": 605,
    "item_type": 6
  },
  {
    "item_id": 99,
    "price_id": 999578,
    "amount": 125,
    "id": 606,
    "item_type": 6
  },
  {
    "item_id": 99,
    "price_id": 999579,
    "amount": 130,
    "id": 607,
    "item_type": 6
  },
  {
    "item_id": 99,
    "price_id": 999580,
    "amount": 135,
    "id": 608,
    "item_type": 6
  },
  {
    "item_id": 902,
    "price_id": 999581,
    "amount": 1,
    "id": 609,
    "item_type": 6
  },
  {
    "item_id": 902,
    "price_id": 999582,
    "amount": 2,
    "id": 610,
    "item_type": 6
  },
  {
    "item_id": 902,
    "price_id": 999583,
    "amount": 4,
    "id": 611,
    "item_type": 6
  },
  {
    "item_id": 902,
    "price_id": 999584,
    "amount": 6,
    "id": 612,
    "item_type": 6
  },
  {
    "item_id": 908,
    "price_id": 999585,
    "amount": 1,
    "id": 613,
    "item_type": 6
  },
  {
    "item_id": 908,
    "price_id": 999586,
    "amount": 2,
    "id": 614,
    "item_type": 6
  },
  {
    "item_id": 908,
    "price_id": 999587,
    "amount": 4,
    "id": 615,
    "item_type": 6
  },
  {
    "item_id": 908,
    "price_id": 999588,
    "amount": 6,
    "id": 616,
    "item_type": 6
  },
  {
    "item_id": 960,
    "price_id": 999589,
    "amount": 1,
    "id": 617,
    "item_type": 6
  },
  {
    "item_id": 960,
    "price_id": 999590,
    "amount": 2,
    "id": 618,
    "item_type": 6
  },
  {
    "item_id": 960,
    "price_id": 999591,
    "amount": 4,
    "id": 619,
    "item_type": 6
  },
  {
    "item_id": 960,
    "price_id": 999592,
    "amount": 6,
    "id": 620,
    "item_type": 6
  },
  {
    "item_id": 919,
    "price_id": 999593,
    "amount": 1,
    "id": 621,
    "item_type": 6
  },
  {
    "item_id": 919,
    "price_id": 999594,
    "amount": 2,
    "id": 622,
    "item_type": 6
  },
  {
    "item_id": 919,
    "price_id": 999595,
    "amount": 4,
    "id": 623,
    "item_type": 6
  },
  {
    "item_id": 919,
    "price_id": 999596,
    "amount": 6,
    "id": 624,
    "item_type": 6
  },
  {
    "item_id": 9000,
    "price_id": 999597,
    "amount": 1,
    "id": 625,
    "item_type": 6
  },
  {
    "item_id": 9000,
    "price_id": 999598,
    "amount": 2,
    "id": 626,
    "item_type": 6
  },
  {
    "item_id": 901,
    "price_id": 999599,
    "amount": 1,
    "id": 627,
    "item_type": 6
  },
  {
    "item_id": 993,
    "price_id": 999600,
    "amount": 1,
    "id": 628,
    "item_type": 6
  },
  {
    "item_id": 909,
    "price_id": 999601,
    "amount": 1,
    "id": 629,
    "item_type": 6
  },
  {
    "item_id": 913,
    "price_id": 999602,
    "amount": 1,
    "id": 630,
    "item_type": 6
  },
  {
    "item_id": 930,
    "price_id": 999603,
    "amount": 1,
    "id": 631,
    "item_type": 6
  },
  {
    "item_id": 927,
    "price_id": 999604,
    "amount": 1,
    "id": 632,
    "item_type": 6
  },
  {
    "item_id": 9001,
    "price_id": 999605,
    "amount": 1,
    "id": 633,
    "item_type": 6
  },
  {
    "item_id": 9001,
    "price_id": 999606,
    "amount": 2,
    "id": 634,
    "item_type": 6
  },
  {
    "item_id": 9002,
    "price_id": 999607,
    "amount": 1,
    "id": 635,
    "item_type": 6
  },
  {
    "item_id": 9002,
    "price_id": 999608,
    "amount": 2,
    "id": 636,
    "item_type": 6
  }
]